{
  "base_price": 7450,
  "beamstation_catalog_url": "https://beamstation.com/datasets",
  "beamstation_origin": "https://beamstation.com",
  "category_group_name": "Restaurants",
  "config_category": "census",
  "config_description": "Complete state-level restaurant data for Oklahoma. This dataset captures every active restaurant listing filtered by the Restaurants category group, providing comprehensive coverage for statewide market research. Includes ratings, reviews, sentiment data, and competitive metrics. Refreshed weekly.",
  "config_name": "All Restaurants in Oklahoma, US",
  "export_job_id": "a3564ac0-569b-46ce-9a70-cb0df6415fb5",
  "github_org": "Beamstation-Datasets",
  "id_short": 568940,
  "location_name": "Oklahoma",
  "location_type": "state",
  "repo_name": "all-restaurants-in-oklahoma-us-sample-568940",
  "sample_b2_path": "b2-export:BeamStation-ExportFiles/568940/beamstation_568940_restaurants-us-ok_SAMPLE_DIST.csv",
  "sample_pct": 10.0,
  "sample_records": 933,
  "sample_sha256": "5b8a31bd8cf53cd68152a5a26d861a7080877871a07e55c87bf3c5828c2d3c7a",
  "sample_size_bytes": 2738757,
  "total_records": 9330,
  "updated_at": "2026-04-07T15:40:19.076152+00:00"
}